papertrail/__init__.py
papertrail/admin.py
papertrail/apps.py
papertrail/models.py
papertrail/signals.py
papertrail/tests.py
papertrail/migrations/0001_initial.py
papertrail/migrations/__init__.py
papertrail/templatetags/__init__.py
papertrail/templatetags/papertrail.py
settings/__init__.py
settings/base.py
settings/local.py
settings/testing.py
ddaemon_django_papertrail-0.1.3.dist-info/LICENSE
ddaemon_django_papertrail-0.1.3.dist-info/METADATA
ddaemon_django_papertrail-0.1.3.dist-info/WHEEL
ddaemon_django_papertrail-0.1.3.dist-info/top_level.txt
ddaemon_django_papertrail-0.1.3.dist-info/RECORD
